apollogize/__init__.py
apollogize/apollogize.py
apollogize/version.py
apollogize-0.0.6.dist-info/LICENSE.txt
apollogize-0.0.6.dist-info/METADATA
apollogize-0.0.6.dist-info/WHEEL
apollogize-0.0.6.dist-info/entry_points.txt
apollogize-0.0.6.dist-info/top_level.txt
apollogize-0.0.6.dist-info/RECORD
