Metadata-Version: 2.1
Name: apollogize
Version: 0.0.6
Summary: Apollogize is a command line tool which assists the employers who forgot to check-in and check-out in Apollo app.
Home-page: https://github.com/zacfeng/Apollogize
Author: Zac Chien
Author-email: fengying0709@gmail.com
License: GPLv3
Platform: UNKNOWN
Classifier: Programming Language :: Python :: 3
Classifier: License :: OSI Approved :: MIT License
Classifier: Operating System :: OS Independent
Requires-Python: >=3.6
License-File: LICENSE.txt
Requires-Dist: pendulum (==2.1.2)
Requires-Dist: prompt-toolkit (==3.0.23)
Requires-Dist: requests (==2.25.0)
